LICENSE
README.md
changelog.md
ocrmypdf_papermerge/__init__.py
ocrmypdf_papermerge/generate_preview.py
ocrmypdf_papermerge/generate_svg.py
ocrmypdf_papermerge/hocr.py
ocrmypdf_papermerge/image.py
ocrmypdf_papermerge/plugin.py
ocrmypdf_papermerge/render.py
ocrmypdf_papermerge/templates/page.html.j2
ocrmypdf_papermerge/templates/page.svg.j2
ocrmypdf_papermerge/utils.py
ocrmypdf_papermerge-0.7.1.dist-info/LICENSE
ocrmypdf_papermerge-0.7.1.dist-info/METADATA
ocrmypdf_papermerge-0.7.1.dist-info/WHEEL
ocrmypdf_papermerge-0.7.1.dist-info/RECORD
