Metadata-Version: 2.1
Name: ocrmypdf-papermerge
Version: 0.7.1
Summary: OCRmyPDF plugin to generate SVG files for Papermerge
Home-page: https://github.com/papermerge/OCRmyPDF_papermerge
License: Apache-2.0
Keywords: OCR,PDF,OCRmyPDF,Document Management System
Author: Eugen Ciur
Author-email: eugen@papermerge.com
Maintainer: Eugen Ciur
Maintainer-email: eugen@papermerge.com
Requires-Python: >=3.13,<4.0
Classifier: License :: OSI Approved :: Apache Software License
Classifier: Operating System :: OS Independent
Classifier: Programming Language :: Python
Classifier: Programming Language :: Python :: 3
Classifier: Programming Language :: Python :: 3.13
Classifier: Programming Language :: Python :: 3 :: Only
Classifier: Programming Language :: Python :: 3.10
Classifier: Programming Language :: Python :: 3.11
Classifier: Programming Language :: Python :: 3.7
Classifier: Programming Language :: Python :: 3.8
Classifier: Programming Language :: Python :: 3.9
Requires-Dist: Jinja2 (>=3.1,<4.0)
Requires-Dist: lxml (>=5.3,<6.0)
Requires-Dist: ocrmypdf (>=16.6,<17.0)
Project-URL: Repository, https://github.com/papermerge/OCRmyPDF_papermerge
